{
  "pincode": "600126",
  "stateCode": "33",
  "districtCode": "TNCHE",
  "scrapedAt": "2026-06-01T05:38:49.090Z",
  "totalRecords": 10,
  "records": [
    {
      "pincode": "600126",
      "enrollmentNo": "331800000933GPO",
      "name": "Kannan",
      "stateCode": "33",
      "districtCode": "",
      "qualification": "",
      "address": "",
      "district": "",
      "city": "",
      "pinCode": "600126",
      "mobileNo": "",
      "emailId": "",
      "status": "",
      "_raw": {
        "enrlNo": "331800000933GPO",
        "trpNam": "Kannan",
        "stCd": "33",
        "dstCd": null,
        "pinCd": null,
        "cntctNo": "7358447381",
        "emailId": "sksassociate14@gmail.com",
        "ctgry": "GOPDC",
        "adrs": {
          "bldNo": "9/443",
          "fltNo": "S1 SECOND FLOOR",
          "bldName": "SHABARI ARUL APARTMENTS",
          "road": "INDIRA NAGAR KULKARAI STREET EXTN",
          "locality": "VENGAIVASAL",
          "district": "TNCHE",
          "pinCd": "600126",
          "addr": "S1 SECOND FLOOR,9/443,SHABARI ARUL APARTMENTS,INDIRA NAGAR KULKARAI STREET EXTN,VENGAIVASAL"
        },
        "searchType": null,
        "authTokn": null,
        "status": "A"
      }
    },
    {
      "pincode": "600126",
      "enrollmentNo": "331800002037GPW",
      "name": "Sarathkumar",
      "stateCode": "33",
      "districtCode": "",
      "qualification": "",
      "address": "",
      "district": "",
      "city": "",
      "pinCode": "600126",
      "mobileNo": "",
      "emailId": "",
      "status": "",
      "_raw": {
        "enrlNo": "331800002037GPW",
        "trpNam": "Sarathkumar",
        "stCd": "33",
        "dstCd": null,
        "pinCd": null,
        "cntctNo": "9962421032",
        "emailId": "tcsarath91@gmail.com",
        "ctgry": "GOPDC",
        "adrs": {
          "bldNo": "5/302",
          "fltNo": null,
          "bldName": null,
          "road": "Senthamizh Nagar, First Street",
          "locality": "Sithalappakkam",
          "district": "TNCHE",
          "pinCd": "600126",
          "addr": "5/302,Senthamizh Nagar, First Street,Sithalappakkam"
        },
        "searchType": null,
        "authTokn": null,
        "status": "A"
      }
    },
    {
      "pincode": "600126",
      "enrollmentNo": "331800002545GPP",
      "name": "BILAL",
      "stateCode": "33",
      "districtCode": "",
      "qualification": "",
      "address": "",
      "district": "",
      "city": "",
      "pinCode": "600126",
      "mobileNo": "",
      "emailId": "",
      "status": "",
      "_raw": {
        "enrlNo": "331800002545GPP",
        "trpNam": "BILAL",
        "stCd": "33",
        "dstCd": null,
        "pinCd": null,
        "cntctNo": "9176431519",
        "emailId": "p.mohammedbilal@gmail.com",
        "ctgry": "GOPDC",
        "adrs": {
          "bldNo": "No 576",
          "fltNo": "TNHB COLONY",
          "bldName": "",
          "road": "SITHALAPAKKAM",
          "locality": "CHENAI",
          "district": "TNCHE",
          "pinCd": "600126",
          "addr": "TNHB COLONY,No 576,SITHALAPAKKAM,CHENAI"
        },
        "searchType": null,
        "authTokn": null,
        "status": "A"
      }
    },
    {
      "pincode": "600126",
      "enrollmentNo": "331900004850GPO",
      "name": "Arun Prassath A C",
      "stateCode": "33",
      "districtCode": "",
      "qualification": "",
      "address": "",
      "district": "",
      "city": "",
      "pinCode": "600126",
      "mobileNo": "",
      "emailId": "",
      "status": "",
      "_raw": {
        "enrlNo": "331900004850GPO",
        "trpNam": "Arun Prassath A C",
        "stCd": "33",
        "dstCd": null,
        "pinCd": null,
        "cntctNo": "9159916156",
        "emailId": "acarunprassath@gmail.com",
        "ctgry": "GOPDC",
        "adrs": {
          "bldNo": "B-18 F1 and F2",
          "fltNo": "First Floor",
          "bldName": "Annai Avantika Apartments",
          "road": "Vayalveli Road,Anjaneyar Koil Street",
          "locality": "Vengaivasal,Chennai",
          "district": "TNCHE",
          "pinCd": "600126",
          "addr": "First Floor,B-18 F1 and F2,Annai Avantika Apartments,Vayalveli Road,Anjaneyar Koil Street,Vengaivasal,Chennai"
        },
        "searchType": null,
        "authTokn": null,
        "status": "A"
      }
    },
    {
      "pincode": "600126",
      "enrollmentNo": "332000005639GPS",
      "name": "BABU ASHOK KUMAR",
      "stateCode": "33",
      "districtCode": "",
      "qualification": "",
      "address": "",
      "district": "",
      "city": "",
      "pinCode": "600126",
      "mobileNo": "",
      "emailId": "",
      "status": "",
      "_raw": {
        "enrlNo": "332000005639GPS",
        "trpNam": "BABU ASHOK KUMAR",
        "stCd": "33",
        "dstCd": null,
        "pinCd": null,
        "cntctNo": "9884666901",
        "emailId": "movaassociates@gmail.com",
        "ctgry": "GOPDC",
        "adrs": {
          "bldNo": "S1 C Block",
          "fltNo": null,
          "bldName": "Shanmuga Nivas",
          "road": "Sri Ram Nagar",
          "locality": "Kovilancherry",
          "district": "TNCHE",
          "pinCd": "600126",
          "addr": "S1 C Block,Shanmuga Nivas,Sri Ram Nagar,Kovilancherry"
        },
        "searchType": null,
        "authTokn": null,
        "status": "A"
      }
    },
    {
      "pincode": "600126",
      "enrollmentNo": "332100007422GP7",
      "name": "MANICKAM UMAPATHY",
      "stateCode": "33",
      "districtCode": "",
      "qualification": "",
      "address": "",
      "district": "",
      "city": "",
      "pinCode": "600126",
      "mobileNo": "",
      "emailId": "",
      "status": "",
      "_raw": {
        "enrlNo": "332100007422GP7",
        "trpNam": "MANICKAM UMAPATHY",
        "stCd": "33",
        "dstCd": null,
        "pinCd": null,
        "cntctNo": "9444056695",
        "emailId": "umapathymanickam1959@gmail.com",
        "ctgry": "GPDBA",
        "adrs": {
          "bldNo": "New No.3/Old No.92",
          "fltNo": null,
          "bldName": null,
          "road": "Anna Nagar, Madambakkam Main Road",
          "locality": "Madambakkam",
          "district": "TNCHE",
          "pinCd": "600126",
          "addr": "New No.3/Old No.92,Anna Nagar, Madambakkam Main Road,Madambakkam"
        },
        "searchType": null,
        "authTokn": null,
        "status": "A"
      }
    },
    {
      "pincode": "600126",
      "enrollmentNo": "332200007705GPV",
      "name": "RAMU MADHUPRASATH",
      "stateCode": "33",
      "districtCode": "",
      "qualification": "",
      "address": "",
      "district": "",
      "city": "",
      "pinCode": "600126",
      "mobileNo": "",
      "emailId": "",
      "status": "",
      "_raw": {
        "enrlNo": "332200007705GPV",
        "trpNam": "RAMU MADHUPRASATH",
        "stCd": "33",
        "dstCd": null,
        "pinCd": null,
        "cntctNo": "8778614319",
        "emailId": "madhu.gst.practitioner@gmail.com",
        "ctgry": "GPDBA",
        "adrs": {
          "bldNo": "C-5",
          "fltNo": null,
          "bldName": null,
          "road": "NETHAJI STREET",
          "locality": "AGARAMTHEN, EAST THAMBRAM",
          "district": "TNCHE",
          "pinCd": "600126",
          "addr": "C-5,NETHAJI STREET,AGARAMTHEN, EAST THAMBRAM"
        },
        "searchType": null,
        "authTokn": null,
        "status": "A"
      }
    },
    {
      "pincode": "600126",
      "enrollmentNo": "332300008042GP8",
      "name": "A SHYAMALA GOWRI",
      "stateCode": "33",
      "districtCode": "",
      "qualification": "",
      "address": "",
      "district": "",
      "city": "",
      "pinCode": "600126",
      "mobileNo": "",
      "emailId": "",
      "status": "",
      "_raw": {
        "enrlNo": "332300008042GP8",
        "trpNam": "A SHYAMALA GOWRI",
        "stCd": "33",
        "dstCd": null,
        "pinCd": null,
        "cntctNo": "7338952033",
        "emailId": "shyamla.gowri@gmail.com",
        "ctgry": "GOPDC",
        "adrs": {
          "bldNo": "PLOT NO 14A",
          "fltNo": "VIJAY FLATS, F3, FIRST FLOOR",
          "bldName": "",
          "road": "BANK COLONY 1ST STREET, MADAMBAKKAM",
          "locality": "CHENNAI",
          "district": "TNCHE",
          "pinCd": "600126",
          "addr": "VIJAY FLATS, F3, FIRST FLOOR,PLOT NO 14A,BANK COLONY 1ST STREET, MADAMBAKKAM,CHENNAI"
        },
        "searchType": null,
        "authTokn": null,
        "status": "A"
      }
    },
    {
      "pincode": "600126",
      "enrollmentNo": "332400008859GPB",
      "name": "Ramachandran krishnamurthy",
      "stateCode": "33",
      "districtCode": "",
      "qualification": "",
      "address": "",
      "district": "",
      "city": "",
      "pinCode": "600126",
      "mobileNo": "",
      "emailId": "",
      "status": "",
      "_raw": {
        "enrlNo": "332400008859GPB",
        "trpNam": "Ramachandran krishnamurthy",
        "stCd": "33",
        "dstCd": null,
        "pinCd": null,
        "cntctNo": "9500089461",
        "emailId": "rkcon86@gmail.com",
        "ctgry": "GPDBA",
        "adrs": {
          "bldNo": "1I BLOCK A F1",
          "fltNo": null,
          "bldName": "Malligai Apartments",
          "road": "Bala Garden, Manikam Nagar",
          "locality": "Madambakkam",
          "district": "TNCHE",
          "pinCd": "600126",
          "addr": "1I BLOCK A F1,Malligai Apartments,Bala Garden, Manikam Nagar,Madambakkam"
        },
        "searchType": null,
        "authTokn": null,
        "status": "A"
      }
    },
    {
      "pincode": "600126",
      "enrollmentNo": "332400008863GPM",
      "name": "Velmurugan",
      "stateCode": "33",
      "districtCode": "",
      "qualification": "",
      "address": "",
      "district": "",
      "city": "",
      "pinCode": "600126",
      "mobileNo": "",
      "emailId": "",
      "status": "",
      "_raw": {
        "enrlNo": "332400008863GPM",
        "trpNam": "Velmurugan",
        "stCd": "33",
        "dstCd": null,
        "pinCd": null,
        "cntctNo": "9710424572",
        "emailId": "nellaivel1972@gmail.com",
        "ctgry": "DERFU",
        "adrs": {
          "bldNo": "A8",
          "fltNo": "First Floor",
          "bldName": "Nest Mascot",
          "road": "Ottiayambakkam Main Road, Arasankazhani",
          "locality": "Chennai",
          "district": "TNCHE",
          "pinCd": "600126",
          "addr": "First Floor,A8,Nest Mascot,Ottiayambakkam Main Road, Arasankazhani,Chennai"
        },
        "searchType": null,
        "authTokn": null,
        "status": "A"
      }
    }
  ]
}